setuptools_pyecore/__init__.py
setuptools_pyecore/command.py
setuptools_pyecore-0.2.0.dist-info/METADATA
setuptools_pyecore-0.2.0.dist-info/RECORD
setuptools_pyecore-0.2.0.dist-info/WHEEL
setuptools_pyecore-0.2.0.dist-info/entry_points.txt
setuptools_pyecore-0.2.0.dist-info/top_level.txt
