Metadata-Version: 2.1
Name: setuptools-pyecore
Version: 0.2.0
Summary: Setuptools command for generating Python code from PyEcore models.
Home-page: https://github.com/pyecore/setuptools-pyecore
Author: Andreas Schmidl
Author-email: Andreas.Schmidl@gmail.com
License: BSD 3-Clause
Keywords: setuptools model metamodel EMF Ecore code generator
Platform: any
Classifier: Development Status :: 4 - Beta
Classifier: Intended Audience :: Developers
Classifier: Topic :: Software Development
Classifier: License :: OSI Approved :: BSD License
Classifier: Programming Language :: Python :: 3.4
Classifier: Programming Language :: Python :: 3.5
Classifier: Programming Language :: Python :: 3.6
Requires-Python: >=3.4
Requires-Dist: pyecore
Requires-Dist: pyecoregen
